README.rst
arfx/__init__.py
arfx/collect.py
arfx/core.py
arfx/io.py
arfx/lblio.py
arfx/mdaio.py
arfx/migrate.py
arfx/npyio.py
arfx/oephys.py
arfx/pcmio.py
arfx/select.py
arfx/splitter.py
arfx-2.7.1.dist-info/METADATA
arfx-2.7.1.dist-info/WHEEL
arfx-2.7.1.dist-info/entry_points.txt
arfx-2.7.1.dist-info/licenses/COPYING
arfx-2.7.1.dist-info/RECORD
