Metadata-Version: 2.4
Name: arfx
Version: 2.7.1
Summary: Advanced Recording Format Tools
Project-URL: Homepage, https://github.com/melizalab/arfx
Author-email: C Daniel Meliza <dan@meliza.org>
Maintainer-email: C Daniel Meliza <dan@meliza.org>
License: BSD 3-Clause License
License-File: COPYING
Classifier: Development Status :: 5 - Production/Stable
Classifier: Intended Audience :: Science/Research
Classifier: License :: OSI Approved :: BSD License
Classifier: Natural Language :: English
Classifier: Operating System :: MacOS :: MacOS X
Classifier: Operating System :: Microsoft :: Windows
Classifier: Operating System :: POSIX :: Linux
Classifier: Operating System :: Unix
Classifier: Programming Language :: Python
Classifier: Programming Language :: Python :: 3.8
Classifier: Programming Language :: Python :: 3.9
Classifier: Programming Language :: Python :: 3.10
Classifier: Programming Language :: Python :: 3.11
Classifier: Programming Language :: Python :: 3.12
Classifier: Programming Language :: Python :: 3.13
Classifier: Topic :: Scientific/Engineering
Requires-Python: >=3.8
Requires-Dist: arf>=2.7.0
Requires-Dist: ewave>=1.0.7
Requires-Dist: natsort
Requires-Dist: tqdm
